drf_nested_fields/__init__.py
drf_nested_fields/serializers.py
drf_nested_fields/views.py
drf_nested_fields-0.9.5.dist-info/LICENSE.md
drf_nested_fields-0.9.5.dist-info/METADATA
drf_nested_fields-0.9.5.dist-info/WHEEL
drf_nested_fields-0.9.5.dist-info/top_level.txt
drf_nested_fields-0.9.5.dist-info/RECORD
