Metadata-Version: 2.1
Name: drf-nested-fields
Version: 0.9.5
Summary: Nested fields extension for Django REST Framework 3
Home-page: https://github.com/seebass/drf-nested-fields
Author: Sebastian Bredehöft
Author-email: bredehoeft.sebastian@gmail.com
License: MIT
Platform: UNKNOWN
Classifier: Development Status :: 4 - Beta
Classifier: Environment :: Web Environment
Classifier: Framework :: Django
Classifier: Intended Audience :: Developers
Classifier: License :: OSI Approved :: MIT License
Classifier: Operating System :: OS Independent
Classifier: Programming Language :: Python
Classifier: Programming Language :: Python :: 3
Classifier: Topic :: Internet :: WWW/HTTP
Requires-Dist: django (>=1.10)
Requires-Dist: djangorestframework (>=3.4.0)
